odoo/addons/account_move_attachment/__init__.py
odoo/addons/account_move_attachment/__manifest__.py
odoo/addons/account_move_attachment/account_move.py
odoo/addons/account_move_attachment/account_move_view.xml
odoo12_addon_account_move_attachment-12.0.0.1.0.dist-info/METADATA
odoo12_addon_account_move_attachment-12.0.0.1.0.dist-info/WHEEL
odoo12_addon_account_move_attachment-12.0.0.1.0.dist-info/top_level.txt
odoo12_addon_account_move_attachment-12.0.0.1.0.dist-info/RECORD
